notification_mcp/__init__.py
notification_mcp/bark.py
notification_mcp/pushdeer.py
notification_mcp-0.1.3.dist-info/METADATA
notification_mcp-0.1.3.dist-info/WHEEL
notification_mcp-0.1.3.dist-info/entry_points.txt
notification_mcp-0.1.3.dist-info/top_level.txt
notification_mcp-0.1.3.dist-info/RECORD
