Metadata-Version: 2.4
Name: notification-mcp
Version: 0.1.3
Summary: 一个基于 FastMCP 的消息推送工具，支持 PushDeer、Bark 等多种推送渠道
Project-URL: Homepage, https://github.com/ch1y1z1/notification-mcp
Project-URL: Issues, https://github.com/ch1y1z1/notification-mcp/issues
Classifier: Programming Language :: Python :: 3
Classifier: License :: OSI Approved :: MIT License
Classifier: Operating System :: OS Independent
Requires-Python: >=3.12
Requires-Dist: fastmcp>=0.4.1
Requires-Dist: httpx>=0.28.1
